
  // access flags 0x1
  public someSymbol1()Lscala/Symbol;
    NEW scala/StringContext
    DUP
    GETSTATIC scala/runtime/ScalaRunTime$.MODULE$ : Lscala/runtime/ScalaRunTime$;
    ICONST_1
    ANEWARRAY java/lang/String
    DUP
    ICONST_0
    LDC "Symbolic1"
    AASTORE
    INVOKEVIRTUAL scala/runtime/ScalaRunTime$.wrapRefArray ([Ljava/lang/Object;)Lscala/collection/immutable/ArraySeq;
    INVOKESPECIAL scala/StringContext.<init> (Lscala/collection/immutable/Seq;)V
    GETSTATIC scala/collection/immutable/Nil$.MODULE$ : Lscala/collection/immutable/Nil$;
    INVOKEVIRTUAL scala/StringContext.sym (Lscala/collection/immutable/Seq;)Lscala/Symbol;
    ARETURN
    MAXSTACK = 7
    MAXLOCALS = 1


  // access flags 0x1
  public someSymbol2()Lscala/Symbol;
    NEW scala/StringContext
    DUP
    GETSTATIC scala/runtime/ScalaRunTime$.MODULE$ : Lscala/runtime/ScalaRunTime$;
    ICONST_1
    ANEWARRAY java/lang/String
    DUP
    ICONST_0
    LDC "Symbolic2"
    AASTORE
    INVOKEVIRTUAL scala/runtime/ScalaRunTime$.wrapRefArray ([Ljava/lang/Object;)Lscala/collection/immutable/ArraySeq;
    INVOKESPECIAL scala/StringContext.<init> (Lscala/collection/immutable/Seq;)V
    GETSTATIC scala/collection/immutable/Nil$.MODULE$ : Lscala/collection/immutable/Nil$;
    INVOKEVIRTUAL scala/StringContext.sym (Lscala/collection/immutable/Seq;)Lscala/Symbol;
    ARETURN
    MAXSTACK = 7
    MAXLOCALS = 1


  // access flags 0x1
  public sameSymbol1()Lscala/Symbol;
    NEW scala/StringContext
    DUP
    GETSTATIC scala/runtime/ScalaRunTime$.MODULE$ : Lscala/runtime/ScalaRunTime$;
    ICONST_1
    ANEWARRAY java/lang/String
    DUP
    ICONST_0
    LDC "Symbolic1"
    AASTORE
    INVOKEVIRTUAL scala/runtime/ScalaRunTime$.wrapRefArray ([Ljava/lang/Object;)Lscala/collection/immutable/ArraySeq;
    INVOKESPECIAL scala/StringContext.<init> (Lscala/collection/immutable/Seq;)V
    GETSTATIC scala/collection/immutable/Nil$.MODULE$ : Lscala/collection/immutable/Nil$;
    INVOKEVIRTUAL scala/StringContext.sym (Lscala/collection/immutable/Seq;)Lscala/Symbol;
    ARETURN
    MAXSTACK = 7
    MAXLOCALS = 1


  // access flags 0x1
  public someSymbol3()Lscala/Symbol;
    ALOAD 0
    GETFIELD Symbols.someSymbol3 : Lscala/Symbol;
    ARETURN
    MAXSTACK = 1
    MAXLOCALS = 1


  // access flags 0x1
  public <init>()V
    ALOAD 0
    INVOKESPECIAL java/lang/Object.<init> ()V
    ALOAD 0
    NEW scala/StringContext
    DUP
    GETSTATIC scala/runtime/ScalaRunTime$.MODULE$ : Lscala/runtime/ScalaRunTime$;
    ICONST_1
    ANEWARRAY java/lang/String
    DUP
    ICONST_0
    LDC "Symbolic3"
    AASTORE
    INVOKEVIRTUAL scala/runtime/ScalaRunTime$.wrapRefArray ([Ljava/lang/Object;)Lscala/collection/immutable/ArraySeq;
    INVOKESPECIAL scala/StringContext.<init> (Lscala/collection/immutable/Seq;)V
    GETSTATIC scala/collection/immutable/Nil$.MODULE$ : Lscala/collection/immutable/Nil$;
    INVOKEVIRTUAL scala/StringContext.sym (Lscala/collection/immutable/Seq;)Lscala/Symbol;
    PUTFIELD Symbols.someSymbol3 : Lscala/Symbol;
    RETURN
    MAXSTACK = 8
    MAXLOCALS = 1

